{
  "id": "2R9A1407",
  "title": "Little Explorer, Big Fish",
  "image": "./2R9A1407.jpg",
  "alt": "A toddler in a pink and white striped hat and green pants is sitting on a dark tiled floor, facing an aquarium tank. The child is looking intently at a large fish swimming in the clear blue water, surrounded by underwater plants and thin strands of algae. The image captures a moment of discovery, with the child's back towards the viewer, adding a sense of wonder and exploration.",
  "location": "Zoo Leipzig, Leipzig, Germany",
  "date": "2023-09-04",
  "tags": ["childhood", "aquarium", "discovery", "fish", "underwater"],
  "exif": {
    "camera": "Canon EOS R6m2",
    "lens": "RF35mm F1.8 MACRO IS STM",
    "aperture": "1.8",
    "iso": "320",
    "focal_length": "35.0",
    "shutter_speed": "1/60"
  }
}
